zohocrmsdk/__init__.py
zohocrmsdk/src/__init__.py
zohocrmsdk/src/json_details.json
zohocrmsdk/src/com/__init__.py
zohocrmsdk/src/com/zoho/__init__.py
zohocrmsdk/src/com/zoho/api/__init__.py
zohocrmsdk/src/com/zoho/api/authenticator/__init__.py
zohocrmsdk/src/com/zoho/api/authenticator/oauth_token.py
zohocrmsdk/src/com/zoho/api/authenticator/token.py
zohocrmsdk/src/com/zoho/api/authenticator/store/__init__.py
zohocrmsdk/src/com/zoho/api/authenticator/store/db_store.py
zohocrmsdk/src/com/zoho/api/authenticator/store/file_store.py
zohocrmsdk/src/com/zoho/api/authenticator/store/token_store.py
zohocrmsdk/src/com/zoho/api/logger/__init__.py
zohocrmsdk/src/com/zoho/api/logger/logger.py
zohocrmsdk/src/com/zoho/crm/__init__.py
zohocrmsdk/src/com/zoho/crm/api/__init__.py
zohocrmsdk/src/com/zoho/crm/api/header.py
zohocrmsdk/src/com/zoho/crm/api/header_map.py
zohocrmsdk/src/com/zoho/crm/api/initializer.py
zohocrmsdk/src/com/zoho/crm/api/param.py
zohocrmsdk/src/com/zoho/crm/api/parameter_map.py
zohocrmsdk/src/com/zoho/crm/api/request_proxy.py
zohocrmsdk/src/com/zoho/crm/api/sdk_config.py
zohocrmsdk/src/com/zoho/crm/api/user_signature.py
zohocrmsdk/src/com/zoho/crm/api/appointment_preference/__init__.py
zohocrmsdk/src/com/zoho/crm/api/appointment_preference/action_handler.py
zohocrmsdk/src/com/zoho/crm/api/appointment_preference/action_response.py
zohocrmsdk/src/com/zoho/crm/api/appointment_preference/action_wrapper.py
zohocrmsdk/src/com/zoho/crm/api/appointment_preference/api_exception.py
zohocrmsdk/src/com/zoho/crm/api/appointment_preference/appointment_preference.py
zohocrmsdk/src/com/zoho/crm/api/appointment_preference/appointment_preference_operations.py
zohocrmsdk/src/com/zoho/crm/api/appointment_preference/body_wrapper.py
zohocrmsdk/src/com/zoho/crm/api/appointment_preference/deal_record_configuration.py
zohocrmsdk/src/com/zoho/crm/api/appointment_preference/field.py
zohocrmsdk/src/com/zoho/crm/api/appointment_preference/field_mappings.py
zohocrmsdk6_0-8.0.0.dist-info/LICENSE
zohocrmsdk6_0-8.0.0.dist-info/METADATA
zohocrmsdk6_0-8.0.0.dist-info/WHEEL
zohocrmsdk6_0-8.0.0.dist-info/top_level.txt
zohocrmsdk6_0-8.0.0.dist-info/RECORD
